{
    "actors": {
        "_Camera_ShakeCameraActor": {
            "parent": "",
            "modelActor": {
                "resource": {
                    "type": "None"
                },
                "events": [
                    {
                        "actorTerm": {
                            "actorCreate": {}
                        },
                        "actions": [
                            {
                                "createTimer": {
                                    "name": "DestroyActor",
                                    "duration": 1
                                }
                            },
                            {
                                "shakeCamera": {
                                    "value": 14
                                }
                            }
                        ]
                    },
                    {
                        "actorTerm": {
                            "onTimer": {
                                "name": "DestroyActor"
                            }
                        },
                        "actions": [
                            {
                                "destroy": {}
                            }
                        ]
                    }
                ]
            }
        },
        "_Camera_ShakerUnit": {
            "unitActor": {
                "resource": {
                    "type": "GpuAnimation",
                    "name": "arrowtower_missile"
                },
                "events": [
                    {
                        "actorTerm": {
                            "unitSpawn": {}
                        },
                        "actions": [
                            {
                                "create": {
                                    "actor": "_Camera_ShakeCameraActor"
                                }
                            }
                        ]
                    }
                ],
                "modelScale": 0.1
            }
        },
        "_Collectible_Test1": {
            "unitActor": {
                "resource": {
                    "type": "GpuAnimation",
                    "name": "boss_drow_lord_missile_red"
                }
            }
        },
        "_Collectible_Test2": {
            "unitActor": {
                "resource": {
                    "type": "GpuAnimation",
                    "name": "beartrap"
                }
            }
        },
        "_Enemy_GoblinChef": {
            "parent": "_StandardUnit DecayOnDeath",
            "unitActor": {
                "resource": {
                    "type": "GpuAnimation",
                    "name": "goblinchef"
                },
                "events": [
                    {
                        "actorTerm": {
                            "unitAbilityStart": {
                                "ability": "_Enemy_GoblinChef_Attack"
                            }
                        },
                        "actions": [
                            {
                                "playAnimation": {
                                    "clipId": 0
                                }
                            }
                        ]
                    },
                    {
                        "actorTerm": {
                            "unitAbilityStop": {
                                "ability": "_Enemy_GoblinChef_Attack"
                            }
                        },
                        "actions": [
                            {
                                "stopAnimation": {
                                    "clipId": 0
                                }
                            }
                        ]
                    },
                    {
                        "actorTerm": {
                            "unitSpawn": {}
                        },
                        "actions": [
                            {
                                "create": {
                                    "actor": "_FX_Enemy_GoblinChef_Spawn"
                                }
                            }
                        ]
                    }
                ],
                "eventMacros": [
                    "_Enemy_Damage_Effect",
                    "_Enemy_Stunned_Effect"
                ],
                "hostSites": {
                    "StunnedEffectSite": {
                        "offset": {
                            "up": 1
                        }
                    }
                },
                "modelScale": 0.8
            }
        },
        "_Enemy_Hobgoblin": {
            "parent": "_StandardUnit DecayOnDeath",
            "unitActor": {
                "resource": {
                    "type": "GpuAnimation",
                    "name": "hobgoblin"
                },
                "events": [
                    {
                        "actorTerm": {
                            "unitSpawn": {}
                        },
                        "actions": [
                            {
                                "create": {
                                    "actor": "_FX_Enemy_Hobgoblin_Spawn"
                                }
                            }
                        ]
                    },
                    {
                        "actorTerm": {
                            "unitAbilityStart": {
                                "ability": "_Enemy_Hobgoblin_Attack"
                            }
                        },
                        "actions": [
                            {
                                "playAnimation": {
                                    "clipId": 0
                                }
                            }
                        ]
                    },
                    {
                        "actorTerm": {
                            "unitAbilityStop": {
                                "ability": "_Enemy_Hobgoblin_Attack"
                            }
                        },
                        "actions": [
                            {
                                "stopAnimation": {
                                    "clipId": 0
                                }
                            }
                        ]
                    }
                ],
                "eventMacros": [
                    "_Enemy_Damage_Effect",
                    "_Enemy_Stunned_Effect"
                ],
                "hostSites": {
                    "StunnedEffectSite": {
                        "offset": {
                            "up": 1
                        }
                    },
                    "null": {}
                },
                "modelScale": 1.2
            }
        },
        "_EntryDoorway": {
            "unitActor": {
                "resource": {
                    "type": "GpuAnimation",
                    "name": "mineworld_trapdoor"
                },
                "events": [
                    {
                        "actorTerm": {
                            "unitAbilityStart": {
                                "ability": "_DoorwayClose"
                            }
                        },
                        "actions": [
                            {
                                "playAnimation": {
                                    "clipId": 7
                                }
                            },
                            {
                                "createTimer": {
                                    "name": "PauseCloseAnim",
                                    "duration": 0.55
                                }
                            },
                            {
                                "removeTimer": {
                                    "name": "PlayIdleAnim"
                                }
                            }
                        ]
                    },
                    {
                        "actorTerm": {
                            "onTimer": {
                                "name": "PauseCloseAnim"
                            }
                        },
                        "actions": [
                            {
                                "pauseAnimation": {
                                    "clipId": 7
                                }
                            }
                        ]
                    },
                    {
                        "actorTerm": {
                            "unitSpawn": {}
                        },
                        "actions": [
                            {
                                "playAnimation": {
                                    "clipId": 4
                                }
                            },
                            {
                                "createTimer": {
                                    "name": "PlayIdleAnim",
                                    "duration": 0.1,
                                    "repeat": true
                                }
                            }
                        ]
                    },
                    {
                        "actorTerm": {
                            "onTimer": {
                                "name": "PlayIdleAnim"
                            }
                        },
                        "actions": [
                            {
                                "playAnimation": {
                                    "clipId": 4
                                }
                            }
                        ]
                    }
                ]
            }
        },
        "_ExitDoorway": {
            "unitActor": {
                "resource": {
                    "type": "GpuAnimation",
                    "name": "mineworld_trapdoor"
                },
                "events": [
                    {
                        "actorTerm": {
                            "unitAbilityStart": {
                                "ability": "_DoorwayOpen"
                            }
                        },
                        "actions": [
                            {
                                "playAnimation": {
                                    "clipId": 8
                                }
                            },
                            {
                                "createTimer": {
                                    "name": "PauseOpenAnim",
                                    "duration": 0.55
                                }
                            }
                        ]
                    },
                    {
                        "actorTerm": {
                            "onTimer": {
                                "name": "PauseOpenAnim"
                            }
                        },
                        "actions": [
                            {
                                "pauseAnimation": {
                                    "clipId": 8
                                }
                            },
                            {
                                "log": {
                                    "message": "Animation Paused"
                                }
                            }
                        ]
                    }
                ]
            }
        },
        "_FX_Enemy_GoblinChef_Spawn": {
            "modelActor": {
                "resource": {
                    "type": "ParticleAnimation",
                    "name": "vfx_chosen_blindingflash_impact"
                },
                "events": [
                    {
                        "actorTerm": {
                            "actorCreate": {}
                        },
                        "actions": [
                            {
                                "playAnimation": {}
                            },
                            {
                                "createTimer": {
                                    "name": "FailsafeRemove",
                                    "duration": 5
                                }
                            }
                        ]
                    },
                    {
                        "actorTerm": {
                            "animationFinish": {}
                        },
                        "actions": [
                            {
                                "destroy": {}
                            }
                        ]
                    },
                    {
                        "actorTerm": {
                            "onTimer": {
                                "name": "FailsafeRemove"
                            }
                        },
                        "actions": [
                            {
                                "destroy": {}
                            }
                        ]
                    }
                ],
                "hostSiteOperations": [
                    "SOp HoldPosition"
                ]
            }
        },
        "_FX_Enemy_Hobgoblin_Spawn": {
            "modelActor": {
                "resource": {
                    "type": "ParticleAnimation",
                    "name": "vfx_chosen_blindingflash_impact"
                },
                "events": [
                    {
                        "actorTerm": {
                            "actorCreate": {}
                        },
                        "actions": [
                            {
                                "playAnimation": {}
                            },
                            {
                                "createTimer": {
                                    "name": "FailsafeRemove",
                                    "duration": 5
                                }
                            }
                        ]
                    },
                    {
                        "actorTerm": {
                            "animationFinish": {}
                        },
                        "actions": [
                            {
                                "destroy": {}
                            }
                        ]
                    },
                    {
                        "actorTerm": {
                            "onTimer": {
                                "name": "FailsafeRemove"
                            }
                        },
                        "actions": [
                            {
                                "destroy": {}
                            }
                        ]
                    }
                ],
                "hostSiteOperations": [
                    "SOp HoldPosition"
                ]
            }
        },
        "_FX_Enemy_Stun_Impact": {
            "modelActor": {
                "resource": {
                    "type": "ParticleAnimation",
                    "name": "vfx_status_stun_impact"
                },
                "events": [
                    {
                        "actorTerm": {
                            "actorCreate": {}
                        },
                        "actions": [
                            {
                                "playAnimation": {}
                            },
                            {
                                "createTimer": {
                                    "name": "FailsafeRemove",
                                    "duration": 5
                                }
                            }
                        ]
                    },
                    {
                        "actorTerm": {
                            "animationFinish": {}
                        },
                        "actions": [
                            {
                                "destroy": {}
                            }
                        ]
                    },
                    {
                        "actorTerm": {
                            "onTimer": {
                                "name": "FailsafeRemove"
                            }
                        },
                        "actions": [
                            {
                                "destroy": {}
                            }
                        ]
                    }
                ],
                "hostSiteOperations": [
                    "SOp HoldPosition"
                ],
                "modelScale": 2
            }
        },
        "_FX_Enemy_Stunned": {
            "modelActor": {
                "resource": {
                    "type": "ParticleAnimation",
                    "name": "vfx_status_stun"
                },
                "modelScale": 2
            }
        },
        "_FX_Launch_Enemy_GoblinChef": {
            "parent": "_FX Attack SingleTarget",
            "actionActor": {
                "effect": "_Launch_Enemy_GoblinChef"
            }
        },
        "_FX_Launch_PlayerCharacter_Ranged_HeavyAttack": {
            "parent": "_FX Attack SingleTarget",
            "actionActor": {
                "effect": "_Launch_PlayerCharacter_Ranged_HeavyAttack"
            }
        },
        "_FX_Launch_PlayerCharacter_Ranged_LightAttack": {
            "parent": "_FX Attack SingleTarget",
            "actionActor": {
                "effect": "_Launch_PlayerCharacter_Ranged_LightAttack"
            }
        },
        "_FX_PlayerCharacter_Melee_HeavyAttack": {
            "parent": "_FX OneShot SelfRemoving",
            "modelActor": {
                "resource": {
                    "type": "ParticleAnimation",
                    "name": "vfx_ogre_slam_impact_aoe"
                },
                "hostSiteOperations": [
                    "SOp HoldPosition"
                ]
            }
        },
        "_FX_PlayerCharacter_Melee_LightAttack": {
            "parent": "_FX OneShot SelfRemoving",
            "modelActor": {
                "resource": {
                    "type": "ParticleAnimation",
                    "name": "vfx_arrow_tower_hit"
                },
                "hostSiteOperations": [
                    "SOp HoldPosition"
                ],
                "modelScale": 4
            }
        },
        "_Missile_Enemy_GoblinChef": {
            "unitActor": {
                "resource": {
                    "type": "ParticleAnimation",
                    "name": "vfx_arcade_missile_green"
                },
                "modelScale": 0.5
            }
        },
        "_Missile_PlayerCharacter_HeavyAttack": {
            "unitActor": {
                "resource": {
                    "type": "ParticleAnimation",
                    "name": "vfx_arcade_missile_red"
                }
            }
        },
        "_Missile_PlayerCharacter_LightAttack": {
            "unitActor": {
                "resource": {
                    "type": "ParticleAnimation",
                    "name": "vfx_icemage_weapon_missile"
                }
            }
        },
        "_Missile_PlayerCharacter_Melee": {
            "unitActor": {
                "resource": {
                    "type": "GpuAnimation",
                    "name": "dwarfsmith"
                }
            }
        },
        "_Missile_PlayerCharacter_Ranged": {
            "unitActor": {
                "resource": {
                    "type": "GpuAnimation",
                    "name": "arrowtower_unit_rank03"
                }
            }
        },
        "_PlayerCharacter_Melee": {
            "unitActor": {
                "resource": {
                    "type": "GpuAnimation",
                    "name": "dwarfsmith"
                },
                "events": [
                    {
                        "actorTerm": {
                            "unitDeath": {}
                        },
                        "actions": [
                            {
                                "playAnimation": {
                                    "clipId": 1
                                }
                            }
                        ]
                    },
                    {
                        "actorTerm": {
                            "unitAbilityStart": {
                                "ability": "_PlayerCharacter_Melee_LightAttack"
                            }
                        },
                        "actions": [
                            {
                                "playAnimation": {
                                    "clipId": 0
                                }
                            },
                            {
                                "createTimer": {
                                    "name": "DelayedAttack1Spawn",
                                    "duration": 0.3
                                }
                            },
                            {
                                "createTimer": {
                                    "name": "StopLightAttackAnim",
                                    "duration": 0.55
                                }
                            }
                        ]
                    },
                    {
                        "actorTerm": {
                            "unitAbilityStart": {
                                "ability": "_PlayerCharacter_Melee_HeavyAttack"
                            }
                        },
                        "actions": [
                            {
                                "playAnimation": {
                                    "clipId": 4
                                }
                            },
                            {
                                "createTimer": {
                                    "name": "DelayedAttack2Spawn",
                                    "duration": 0.3
                                }
                            },
                            {
                                "createTimer": {
                                    "name": "StopHeavyAttackAnim",
                                    "duration": 0.75
                                }
                            }
                        ]
                    },
                    {
                        "actorTerm": {
                            "onTimer": {
                                "name": "StopLightAttackAnim"
                            }
                        },
                        "actions": [
                            {
                                "stopAnimation": {}
                            }
                        ]
                    },
                    {
                        "actorTerm": {
                            "onTimer": {
                                "name": "StopHeavyAttackTimer"
                            }
                        },
                        "actions": [
                            {
                                "stopAnimation": {
                                    "clipId": 4
                                }
                            }
                        ]
                    },
                    {
                        "actorTerm": {
                            "onTimer": {
                                "name": "DelayedAttack1Spawn"
                            }
                        },
                        "actions": [
                            {
                                "create": {
                                    "actor": "_FX_PlayerCharacter_Melee_LightAttack",
                                    "hostSite": "Melee Attack Host Site"
                                }
                            }
                        ]
                    },
                    {
                        "actorTerm": {
                            "onTimer": {
                                "name": "DelayedAttack2Spawn"
                            }
                        },
                        "actions": [
                            {
                                "create": {
                                    "actor": "_FX_PlayerCharacter_Melee_HeavyAttack"
                                }
                            },
                            {
                                "create": {
                                    "actor": "_Camera_ShakeCameraActor"
                                }
                            }
                        ]
                    },
                    {
                        "actorTerm": {
                            "unitAbilityStop": {
                                "ability": "_PlayerCharacter_Melee_LightAttack"
                            }
                        },
                        "actions": [
                            {
                                "log": {
                                    "type": 0,
                                    "message": "Stopped Melee Light Attack"
                                }
                            }
                        ]
                    },
                    {
                        "actorTerm": {
                            "unitAbilityStop": {
                                "ability": "_PlayerCharacter_Melee_HeavyAttack"
                            }
                        },
                        "actions": [
                            {
                                "log": {
                                    "message": "Stopped Melee Heavy Attack"
                                }
                            }
                        ]
                    },
                    {
                        "actorTerm": {
                            "unitAbilityStart": {
                                "ability": "_PlayerCharacter_Melee_Dash"
                            }
                        },
                        "actions": [
                            {
                                "setVisibility": {}
                            }
                        ]
                    },
                    {
                        "actorTerm": {
                            "unitAbilityStop": {
                                "ability": "_PlayerCharacter_Melee_Dash"
                            }
                        },
                        "actions": [
                            {
                                "setVisibility": {
                                    "visibility": true
                                }
                            },
                            {
                                "log": {
                                    "message": "Normal Visibility"
                                }
                            }
                        ]
                    },
                    {
                        "actorTerm": {
                            "behaviorOn": {
                                "behavior": "_PlayerCharacter_DashEnded"
                            }
                        },
                        "actions": [
                            {
                                "setVisibility": {
                                    "visibility": true
                                }
                            },
                            {
                                "log": {
                                    "message": "Forced Visibility"
                                }
                            }
                        ]
                    }
                ],
                "eventMacros": [
                    "_PlayerCharacter_Invincible"
                ],
                "hostSites": {
                    "Melee Attack Host Site": {
                        "offset": {
                            "forward": 0.8
                        }
                    }
                }
            }
        },
        "_PlayerCharacter_Ranged": {
            "unitActor": {
                "resource": {
                    "type": "GpuAnimation",
                    "name": "arrowtower_unit_rank03"
                },
                "events": [
                    {
                        "actorTerm": {
                            "unitDeath": {}
                        },
                        "actions": [
                            {
                                "playAnimation": {
                                    "clipId": 1
                                }
                            }
                        ]
                    },
                    {
                        "actorTerm": {
                            "unitAbilityStart": {
                                "ability": "_PlayerCharacter_Ranged_LightAttack"
                            }
                        },
                        "actions": [
                            {
                                "playAnimation": {
                                    "clipId": 0
                                }
                            }
                        ]
                    },
                    {
                        "actorTerm": {
                            "unitAbilityStop": {
                                "ability": "_PlayerCharacter_Ranged_LightAttack"
                            }
                        },
                        "actions": [
                            {
                                "stopAnimation": {
                                    "clipId": 0
                                }
                            },
                            {
                                "log": {
                                    "message": "Stopped Ranged Light Attack"
                                }
                            }
                        ]
                    },
                    {
                        "actorTerm": {
                            "unitAbilityStart": {
                                "ability": "_PlayerCharacter_Ranged_HeavyAttack"
                            }
                        },
                        "actions": [
                            {
                                "playAnimation": {
                                    "clipId": 0
                                }
                            }
                        ]
                    },
                    {
                        "actorTerm": {
                            "unitAbilityStop": {
                                "ability": "_PlayerCharacter_Ranged_HeavyAttack"
                            }
                        },
                        "actions": [
                            {
                                "stopAnimation": {
                                    "clipId": 0
                                }
                            },
                            {
                                "log": {
                                    "message": "Stopped Ranged Heavy Attack"
                                }
                            }
                        ]
                    },
                    {
                        "actorTerm": {
                            "unitAbilityStart": {
                                "ability": "_PlayerCharacter_Ranged_Dash"
                            }
                        },
                        "actions": [
                            {
                                "setVisibility": {}
                            }
                        ]
                    },
                    {
                        "actorTerm": {
                            "unitAbilityStop": {
                                "ability": "_PlayerCharacter_Ranged_Dash"
                            }
                        },
                        "actions": [
                            {
                                "setVisibility": {
                                    "visibility": true
                                }
                            },
                            {
                                "log": {
                                    "message": "Normal Visibility"
                                }
                            }
                        ]
                    },
                    {
                        "actorTerm": {
                            "behaviorOn": {
                                "behavior": "_PlayerCharacter_DashEnded"
                            }
                        },
                        "actions": [
                            {
                                "setVisibility": {
                                    "visibility": true
                                }
                            },
                            {
                                "log": {
                                    "message": "Forced Visiblility"
                                }
                            }
                        ]
                    }
                ],
                "eventMacros": [
                    "_PlayerCharacter_Invincible"
                ],
                "hostSites": {
                    "SiteHit": {
                        "offset": {
                            "forward": 0.1,
                            "up": 0.375
                        }
                    },
                    "SiteWeapon": {
                        "offset": {
                            "forward": 0.5,
                            "up": 0.5
                        }
                    }
                }
            }
        },
        "_Wall_BreakableWall": {
            "unitActor": {
                "resource": {
                    "type": "GpuAnimation",
                    "name": "misc_crate"
                },
                "hostSites": {
                    "SiteHit": {
                        "offset": {
                            "forward": 0.1,
                            "up": 0.375
                        }
                    }
                },
                "modelScale": 2.5
            }
        },
        "_Wall_Doorway": {
            "unitActor": {
                "resource": {
                    "type": "GpuAnimation",
                    "name": "barracks_rank01"
                },
                "hostSites": {
                    "SiteHit": {
                        "offset": {
                            "forward": 0.1,
                            "up": 0.375
                        }
                    }
                }
            }
        },
        "_Wall_SolidWall": {
            "unitActor": {
                "resource": {
                    "type": "GpuAnimation",
                    "name": "forestworld_castleset_wall_tower"
                },
                "hostSites": {
                    "SiteHit": {
                        "offset": {
                            "forward": 0.1,
                            "up": 0.375
                        }
                    }
                },
                "modelScale": 1.5
            }
        },
        "__DebugMarkerUnit": {
            "unitActor": {
                "resource": {
                    "type": "GpuAnimation",
                    "name": "arrowtower_rank03"
                }
            }
        }
    },
    "actorEventMacros": {
        "_Enemy_Damage_Effect": {
            "events": [
                {
                    "actorTerm": {
                        "behaviorOn": {
                            "behavior": "_Enemy_Damage_Taken"
                        }
                    },
                    "actions": [
                        {
                            "applyMeshEffect": {
                                "effect": "BloodThirsty"
                            }
                        }
                    ]
                },
                {
                    "actorTerm": {
                        "behaviorOff": {
                            "behavior": "_Enemy_Damage_Taken"
                        }
                    },
                    "actions": [
                        {
                            "removeMeshEffect": {
                                "effect": "BloodThirsty"
                            }
                        }
                    ]
                }
            ]
        },
        "_Enemy_Stunned_Effect": {
            "events": [
                {
                    "actorTerm": {
                        "behaviorOn": {
                            "behavior": "_Enemy_Stunned"
                        }
                    },
                    "actions": [
                        {
                            "create": {
                                "actor": "_FX_Enemy_Stun_Impact"
                            }
                        },
                        {
                            "create": {
                                "actor": "_FX_Enemy_Stunned",
                                "hostSite": "StunnedEffectSite"
                            }
                        }
                    ]
                },
                {
                    "actorTerm": {
                        "behaviorOff": {
                            "behavior": "_Enemy_Stunned"
                        }
                    },
                    "actions": [
                        {
                            "destroy": {
                                "actor": "_FX_Enemy_Stunned"
                            }
                        }
                    ]
                }
            ]
        },
        "_PlayerCharacter_Invincible": {
            "events": [
                {
                    "actorTerm": {
                        "behaviorOn": {
                            "behavior": "_PlayerCharacter_Invincible"
                        }
                    },
                    "actions": [
                        {
                            "createTimer": {
                                "name": "FlashPlayerMeshOff",
                                "duration": 0.1,
                                "repeat": false
                            }
                        },
                        {
                            "log": {
                                "message": "Player Invincible"
                            }
                        }
                    ]
                },
                {
                    "actorTerm": {
                        "behaviorOff": {
                            "behavior": "_PlayerCharacter_Invincible"
                        }
                    },
                    "actions": [
                        {
                            "removeTimer": {
                                "name": "FlashPlayerMeshOff"
                            }
                        },
                        {
                            "removeTimer": {
                                "name": "FlashPlayerMeshOn"
                            }
                        },
                        {
                            "setVisibility": {
                                "visibility": true
                            }
                        },
                        {
                            "log": {
                                "message": "Invincibility Removed"
                            }
                        }
                    ]
                },
                {
                    "actorTerm": {
                        "onTimer": {
                            "name": "FlashPlayerMeshOff"
                        }
                    },
                    "actions": [
                        {
                            "setVisibility": {
                                "visibility": false
                            }
                        },
                        {
                            "createTimer": {
                                "name": "FlashPlayerMeshOn",
                                "duration": 0.1
                            }
                        }
                    ]
                },
                {
                    "actorTerm": {
                        "onTimer": {
                            "name": "FlashPlayerMeshOn"
                        }
                    },
                    "actions": [
                        {
                            "setVisibility": {
                                "visibility": true
                            }
                        },
                        {
                            "createTimer": {
                                "name": "FlashPlayerMeshOff",
                                "duration": 0.1
                            }
                        }
                    ]
                }
            ]
        }
    }
}